eobox/__init__.py
eobox/ml/__init__.py
eobox/ml/clf_extension.py
eobox/ml/plot.py
eobox/raster/__init__.py
eobox/raster/cube.py
eobox/raster/extraction.py
eobox/raster/gdalutils.py
eobox/raster/rasterprocessing.py
eobox/raster/utils.py
eobox/sampledata/__init__.py
eobox/sampledata/base.py
eobox/sampledata/data/lsts/LE70350322008118EDC00/LE70350322008118EDC00_b3.tif
eobox/sampledata/data/lsts/LE70350322008118EDC00/LE70350322008118EDC00_b4.tif
eobox/sampledata/data/lsts/LE70350322008118EDC00/LE70350322008118EDC00_b5.tif
eobox/sampledata/data/lsts/LE70350322008118EDC00/LE70350322008118EDC00_fmask.tif
eobox/sampledata/data/lsts/LE70350322008150EDC00/LE70350322008150EDC00_b3.tif
eobox/sampledata/data/lsts/LE70350322008150EDC00/LE70350322008150EDC00_b4.tif
eobox/sampledata/data/lsts/LE70350322008150EDC00/LE70350322008150EDC00_b5.tif
eobox/sampledata/data/lsts/LE70350322008150EDC00/LE70350322008150EDC00_fmask.tif
eobox/sampledata/data/lsts/LE70350322008166EDC00/LE70350322008166EDC00_b3.tif
eobox/sampledata/data/lsts/LE70350322008166EDC00/LE70350322008166EDC00_b4.tif
eobox/sampledata/data/lsts/LE70350322008166EDC00/LE70350322008166EDC00_b5.tif
eobox/sampledata/data/lsts/LE70350322008166EDC00/LE70350322008166EDC00_fmask.tif
eobox/sampledata/data/lsts/LE70350322008182EDC00/LE70350322008182EDC00_b3.tif
eobox/sampledata/data/lsts/LE70350322008182EDC00/LE70350322008182EDC00_b4.tif
eobox/sampledata/data/lsts/LE70350322008182EDC00/LE70350322008182EDC00_b5.tif
eobox/sampledata/data/lsts/LE70350322008182EDC00/LE70350322008182EDC00_fmask.tif
eobox/sampledata/data/lsts/LE70350322008198EDC00/LE70350322008198EDC00_b3.tif
eobox/sampledata/data/lsts/LE70350322008198EDC00/LE70350322008198EDC00_b4.tif
eobox/sampledata/data/lsts/LE70350322008198EDC00/LE70350322008198EDC00_b5.tif
eobox/sampledata/data/lsts/LE70350322008198EDC00/LE70350322008198EDC00_fmask.tif
eobox/sampledata/data/lsts/LE70350322008214EDC00/LE70350322008214EDC00_b3.tif
eobox-0.3.2.dist-info/LICENSE
eobox-0.3.2.dist-info/METADATA
eobox-0.3.2.dist-info/WHEEL
eobox-0.3.2.dist-info/top_level.txt
eobox-0.3.2.dist-info/RECORD
