Metadata-Version: 2.1
Name: eobox
Version: 0.3.2
Summary: A toolbox for processing earth observation data with Python.
Home-page: https://github.com/benmack/eo-box
Author: Benjamin Mack
Author-email: ben8mack@gmail.com
License: MIT
Platform: UNKNOWN
Requires-Python: >=3.5
Requires-Dist: gdal
Requires-Dist: geopandas
Requires-Dist: matplotlib
Requires-Dist: numpy
Requires-Dist: pandas
Requires-Dist: rasterio
Requires-Dist: seaborn
Requires-Dist: tqdm
